torch_rolx/__init__.py
torch_rolx/refex.py
torch_rolx/rolx.py
torch_rolx/test_intergration.py
torch_rolx/test_refex.py
torch_rolx/test_rolx.py
torch_rolx-0.1.0.dist-info/METADATA
torch_rolx-0.1.0.dist-info/WHEEL
torch_rolx-0.1.0.dist-info/RECORD
