Metadata-Version: 2.3
Name: torch-rolx
Version: 0.1.0
Summary: 
License: MIT
Author: Command M
Requires-Python: >=3.12
Classifier: License :: OSI Approved :: MIT License
Classifier: Programming Language :: Python :: 3
Classifier: Programming Language :: Python :: 3.12
Classifier: Programming Language :: Python :: 3.13
